Systeminfo/__init__.py
Systeminfo/system_Info.py
systeminfo_python3-0.1.1.dist-info/LICENSE.md
systeminfo_python3-0.1.1.dist-info/METADATA
systeminfo_python3-0.1.1.dist-info/WHEEL
systeminfo_python3-0.1.1.dist-info/top_level.txt
systeminfo_python3-0.1.1.dist-info/RECORD
