Metadata-Version: 2.1
Name: systeminfo-python3
Version: 0.1.1
Summary: A package that provides system information for your device.
Home-page: https://github.com/jasserabdou/SystemInfo-Python3-Package
Author: Jasser Abdelfattah
Author-email: jasserabdelfattah12@gmail.com
Keywords: python,systeminfo
Classifier: Development Status :: 1 - Planning
Classifier: Intended Audience :: Developers
Classifier: Programming Language :: Python :: 3
Classifier: Operating System :: Unix
Classifier: Operating System :: MacOS :: MacOS X
Classifier: Operating System :: Microsoft :: Windows
License-File: LICENSE.md
Requires-Dist: psutil
Requires-Dist: py-cpuinfo
Requires-Dist: gputil
